fire_detector/YoloDetector.py
fire_detector/__init__.py
fire_detector/image_detect.py
fire_detector/model_loader.py
fire_detector/modules.py
fire_detector/path_utils.py
fire_detector/video_detect.py
fire_detector/yolo_track.py
fire_detector/models/fire_resnet18_fp16.pth
fire_detector/models/light_yolov8_flame.pt
fire_detector-1.0.3.dist-info/METADATA
fire_detector-1.0.3.dist-info/WHEEL
fire_detector-1.0.3.dist-info/top_level.txt
fire_detector-1.0.3.dist-info/RECORD
