Metadata-Version: 2.4
Name: fire_detector
Version: 1.0.3
Summary: Deep Learning Fire Detection 
Author: WS
Requires-Python: >=3.8
Requires-Dist: torch
Requires-Dist: torchvision
Requires-Dist: Pillow
Requires-Dist: ultralytics
Dynamic: author
Dynamic: requires-dist
Dynamic: requires-python
Dynamic: summary
